azure/communication/administration/__init__.py
azure/communication/administration/_communication_identity_client.py
azure/communication/administration/_phone_number_administration_client.py
azure/communication/administration/_polling.py
azure/communication/administration/_version.py
azure/communication/administration/_identity/__init__.py
azure/communication/administration/_identity/_generated/__init__.py
azure/communication/administration/_identity/_generated/_communication_identity_client.py
azure/communication/administration/_identity/_generated/_configuration.py
azure/communication/administration/_identity/_generated/aio/__init__.py
azure/communication/administration/_identity/_generated/aio/_communication_identity_client.py
azure/communication/administration/_identity/_generated/aio/_configuration.py
azure/communication/administration/_identity/_generated/aio/operations/__init__.py
azure/communication/administration/_identity/_generated/aio/operations/_communication_identity_operations.py
azure/communication/administration/_identity/_generated/models/__init__.py
azure/communication/administration/_identity/_generated/models/_models.py
azure/communication/administration/_identity/_generated/models/_models_py3.py
azure/communication/administration/_identity/_generated/operations/__init__.py
azure/communication/administration/_identity/_generated/operations/_communication_identity_operations.py
azure/communication/administration/_phonenumber/__init__.py
azure/communication/administration/_phonenumber/_generated/__init__.py
azure/communication/administration/_phonenumber/_generated/_configuration.py
azure/communication/administration/_phonenumber/_generated/_phone_number_administration_service.py
azure/communication/administration/_phonenumber/_generated/aio/__init__.py
azure/communication/administration/_phonenumber/_generated/aio/_configuration_async.py
azure/communication/administration/_phonenumber/_generated/aio/_phone_number_administration_service_async.py
azure_communication_administration-1.0.0b4.dist-info/LICENSE.txt
azure_communication_administration-1.0.0b4.dist-info/METADATA
azure_communication_administration-1.0.0b4.dist-info/WHEEL
azure_communication_administration-1.0.0b4.dist-info/top_level.txt
azure_communication_administration-1.0.0b4.dist-info/RECORD
