Metadata-Version: 2.1
Name: azure-communication-administration
Version: 1.0.0b4
Summary: Microsoft Azure Communication Administration Service Client Library for Python
Home-page: https://github.com/Azure/azure-sdk-for-python
Author: Microsoft Corporation
Author-email: azuresdkengsysadmins@microsoft.com
License: MIT License
Project-URL: Bug Reports, https://github.com/Azure/azure-sdk-for-python/issues
Project-URL: Source, https://github.com/Azure/azure-sdk-for-python
Platform: UNKNOWN
Classifier: Development Status :: 4 - Beta
Classifier: Programming Language :: Python
Classifier: Programming Language :: Python :: 2
Classifier: Programming Language :: Python :: 2.7
Classifier: Programming Language :: Python :: 3
Classifier: Programming Language :: Python :: 3.4
Classifier: Programming Language :: Python :: 3.5
Classifier: Programming Language :: Python :: 3.6
Classifier: Programming Language :: Python :: 3.7
Classifier: Programming Language :: Python :: 3.8
Classifier: License :: OSI Approved :: MIT License
Requires-Dist: msrest (>=0.6.0)
Requires-Dist: azure-core (<2.0.0,>=1.6.0)
Requires-Dist: azure-communication-nspkg ; python_version<'3.0'
